pgtransaction/__init__.py
pgtransaction/config.py
pgtransaction/py.typed
pgtransaction/transaction.py
pgtransaction/version.py
django_pgtransaction-2.0.0.dist-info/LICENSE
django_pgtransaction-2.0.0.dist-info/METADATA
django_pgtransaction-2.0.0.dist-info/WHEEL
django_pgtransaction-2.0.0.dist-info/RECORD
