Metadata-Version: 2.1
Name: django-pgtransaction
Version: 2.0.0
Summary: A context manager/decorator which extends Django's atomic function with the ability to set isolation level and retries for a given transaction.
Home-page: https://github.com/AmbitionEng/django-pgtransaction
License: BSD-3-Clause
Author: Paul Gilmartin
Requires-Python: >=3.9.0,<4
Classifier: Framework :: Django
Classifier: Framework :: Django :: 4.2
Classifier: Framework :: Django :: 5.0
Classifier: Framework :: Django :: 5.1
Classifier: Intended Audience :: Developers
Classifier: License :: OSI Approved :: BSD License
Classifier: Operating System :: OS Independent
Classifier: Programming Language :: Python
Classifier: Programming Language :: Python :: 3
Classifier: Programming Language :: Python :: 3.9
Classifier: Programming Language :: Python :: 3.10
Classifier: Programming Language :: Python :: 3.11
Classifier: Programming Language :: Python :: 3.12
Classifier: Programming Language :: Python :: 3.13
Classifier: Programming Language :: Python :: 3 :: Only
Requires-Dist: django (>=4)
Project-URL: Documentation, https://django-pgtransaction.readthedocs.io
Project-URL: Repository, https://github.com/AmbitionEng/django-pgtransaction
